odoo/addons/dms/README.rst
odoo/addons/dms/__init__.py
odoo/addons/dms/__manifest__.py
odoo/addons/dms/actions/file.xml
odoo/addons/dms/controllers/__init__.py
odoo/addons/dms/controllers/main.py
odoo/addons/dms/controllers/portal.py
odoo/addons/dms/data/onboarding_data.xml
odoo/addons/dms/demo/access_group.xml
odoo/addons/dms/demo/category.xml
odoo/addons/dms/demo/directory.xml
odoo/addons/dms/demo/file.xml
odoo/addons/dms/demo/res_users.xml
odoo/addons/dms/demo/storage.xml
odoo/addons/dms/demo/tag.xml
odoo/addons/dms/i18n/de.po
odoo/addons/dms/i18n/dms.pot
odoo/addons/dms/i18n/es.po
odoo/addons/dms/i18n/fa.po
odoo/addons/dms/i18n/fr.po
odoo/addons/dms/i18n/he_IL.po
odoo/addons/dms/i18n/it.po
odoo/addons/dms/i18n/nl.po
odoo/addons/dms/i18n/pt.po
odoo/addons/dms/i18n/pt_BR.po
odoo/addons/dms/i18n/ru.po
odoo/addons/dms/i18n/sv.po
odoo/addons/dms/models/__init__.py
odoo/addons/dms/models/abstract_dms_mixin.py
odoo/addons/dms/models/access_groups.py
odoo/addons/dms/models/base.py
odoo/addons/dms/models/directory.py
odoo/addons/dms/models/dms_category.py
odoo/addons/dms/models/dms_file.py
odoo/addons/dms/models/dms_security_mixin.py
odoo/addons/dms/models/ir_attachment.py
odoo/addons/dms/models/ir_binary.py
odoo/addons/dms/models/mail_thread.py
odoo/addons/dms/models/mixins_thumbnail.py
odoo/addons/dms/models/onboarding_onboarding.py
odoo/addons/dms/models/onboarding_onboarding_step.py
odoo/addons/dms/models/res_company.py
odoo/addons/dms/models/res_config_settings.py
odoo/addons/dms/models/storage.py
odoo/addons/dms/models/tag.py
odoo/addons/dms/readme/CONFIGURE.md
odoo/addons/dms/readme/CONTRIBUTORS.md
odoo/addons/dms/readme/CREDITS.md
odoo/addons/dms/readme/DESCRIPTION.md
odoo/addons/dms/readme/INSTALL.md
odoo/addons/dms/readme/ROADMAP.md
odoo/addons/dms/readme/USAGE.md
odoo/addons/dms/security/ir.model.access.csv
odoo/addons/dms/security/security.xml
odoo/addons/dms/static/description/icon.png
odoo/addons/dms/static/description/icon.svg
odoo_addon_dms-18.0.1.0.7.dist-info/METADATA
odoo_addon_dms-18.0.1.0.7.dist-info/WHEEL
odoo_addon_dms-18.0.1.0.7.dist-info/top_level.txt
odoo_addon_dms-18.0.1.0.7.dist-info/RECORD
