Metadata-Version: 2.1
Name: odoo-addon-dms
Version: 18.0.1.0.7
Requires-Python: >=3.10
Requires-Dist: odoo==18.0.*
Summary: Document Management System for Odoo
Home-page: https://github.com/OCA/dms
License: LGPL-3
Author: MuK IT, Tecnativa, Odoo Community Association (OCA)
Author-email: support@odoo-community.org
Classifier: Programming Language :: Python
Classifier: Framework :: Odoo
Classifier: Framework :: Odoo :: 18.0
Classifier: License :: OSI Approved :: GNU Lesser General Public License v3 (LGPLv3)
